customer_retention_toolkit/api/__init__.py
customer_retention_toolkit/api/api.py
customer_retention_toolkit/db/__init__.py
customer_retention_toolkit/db/schema.py
customer_retention_toolkit/db/sql_interactions.py
customer_retention_toolkit/logger/__init__.py
customer_retention_toolkit/logger/logger.py
customer_retention_toolkit/models/MLWorkflow.py
customer_retention_toolkit/models/__init__.py
customer_retention_toolkit-0.1.1.dist-info/METADATA
customer_retention_toolkit-0.1.1.dist-info/WHEEL
customer_retention_toolkit-0.1.1.dist-info/top_level.txt
customer_retention_toolkit-0.1.1.dist-info/RECORD
