Metadata-Version: 2.1
Name: customer-retention-toolkit
Version: 0.1.1
Summary: A toolkit for customer retention analysis and prediction.
Home-page: https://github.com/davv13/DS223_Project
Author: Tigran Boynagryan, Hayk Khachatryan, Vahagn Tovmasyan, Davit Davtyan, Elen Petrosyan
Author-email: tigran.boynagryan@gmail.com
License: MIT
Keywords: customer retention machine learning
Requires-Dist: annotated-types ==0.6.0
Requires-Dist: anyio ==3.7.1
Requires-Dist: contourpy ==1.1.1
Requires-Dist: cycler ==0.12.1
Requires-Dist: exceptiongroup ==1.1.3
Requires-Dist: fastapi ==0.103.2
Requires-Dist: fonttools ==4.43.1
Requires-Dist: idna ==3.4
Requires-Dist: importlib-resources ==6.1.0
Requires-Dist: kiwisolver ==1.4.5
Requires-Dist: matplotlib ==3.7.3
Requires-Dist: numpy ==1.24.4
Requires-Dist: packaging ==23.2
Requires-Dist: pandas ==2.0.3
Requires-Dist: Pillow ==10.0.1
Requires-Dist: pydantic ==2.4.2
Requires-Dist: pydantic-core ==2.10.1
Requires-Dist: pyparsing ==3.1.1
Requires-Dist: python-dateutil ==2.8.2
Requires-Dist: pytz ==2023.3.post1
Requires-Dist: six ==1.16.0
Requires-Dist: sniffio ==1.3.0
Requires-Dist: starlette ==0.27.0
Requires-Dist: typing-extensions ==4.8.0
Requires-Dist: tzdata ==2023.3
Requires-Dist: zipp ==3.17.0
Requires-Dist: SQLAlchemy ==2.0.22
Requires-Dist: unicorn ==2.0.1.post1
Requires-Dist: uvicorn ==0.23.2
Requires-Dist: watchfiles ==0.21.0
Requires-Dist: websockets ==12.0
Requires-Dist: scikit-learn ==1.3.2
Requires-Dist: requests ==2.31.0
